filezilla/__init__.py
filezilla/__main__.py
filezilla/file_utility.py
filezilla/image_utility.py
filezilla/pdf_utility.py
filezilla-1.2.data/scripts/filezilla
filezilla-1.2.dist-info/METADATA
filezilla-1.2.dist-info/WHEEL
filezilla-1.2.dist-info/top_level.txt
filezilla-1.2.dist-info/RECORD
