Metadata-Version: 2.1
Name: filezilla
Version: 1.2
Summary: File manager
Home-page: UNKNOWN
Author: Gaurav Arora
License: UNKNOWN
Platform: UNKNOWN
Requires-Python: >=3.7
